setup.cfg
setup.py
reselpy_randomizer/__init__.py
reselpy_randomizer/randomizer.py
reselpy_randomizer.egg-info/PKG-INFO
reselpy_randomizer.egg-info/SOURCES.txt
reselpy_randomizer.egg-info/dependency_links.txt
reselpy_randomizer.egg-info/top_level.txt
reselpy_randomizer/data/cities.js
reselpy_randomizer/data/first_names.js
reselpy_randomizer/data/last_names.js
reselpy_randomizer/data/words.js