Metadata-Version: 1.1
Name: reselpy-randomizer
Version: 0.6
Summary: A simple project that provides methods for the return random data
Home-page: https://github.com/reselbob/reselpy_randomizer
Author: Bob Reselman
Author-email: reselbob@gmail.com
License: MIT license
Download-URL: https://github.com/reselbob/reselpy_randomizer/archive/0.6.tar.gz
Keywords: reselpy_randomizer,randomizer,randomization,random
Platform: UNKNOWN
